spt/__init__.py
spt/plot_params.py
spt-0.2.6.dist-info/METADATA
spt-0.2.6.dist-info/WHEEL
spt-0.2.6.dist-info/top_level.txt
spt-0.2.6.dist-info/RECORD
