Metadata-Version: 2.4
Name: spt
Version: 0.2.6
Summary: Scientific Matplotlib plot rcParams configuration template python package.
Home-page: https://github.com/Bit-Part-Young/spt
Author: yangsl
Author-email: yangsl2126@sjtu.edu.cn
Maintainer: yangsl
Maintainer-email: yangsl2126@sjtu.edu.cn
Keywords: scientific plot,Matplotlib
Platform: all
Classifier: Programming Language :: Python :: 3
Requires-Python: >=3.9
Requires-Dist: matplotlib
Provides-Extra: examples
Requires-Dist: numpy; extra == "examples"
Requires-Dist: pandas; extra == "examples"
Requires-Dist: scikit-learn; extra == "examples"
Dynamic: author
Dynamic: author-email
Dynamic: classifier
Dynamic: description
Dynamic: description-content-type
Dynamic: home-page
Dynamic: keywords
Dynamic: maintainer
Dynamic: maintainer-email
Dynamic: platform
Dynamic: provides-extra
Dynamic: requires-dist
Dynamic: requires-python
Dynamic: summary
